dbsconnector/__init__.py
dbsconnector/databases.py
dbsconnector-1.4.dist-info/LICENSE
dbsconnector-1.4.dist-info/METADATA
dbsconnector-1.4.dist-info/WHEEL
dbsconnector-1.4.dist-info/top_level.txt
dbsconnector-1.4.dist-info/RECORD
