Metadata-Version: 2.1
Name: dbsconnector
Version: 1.4
Summary: Python package for connecting and importing data from different DataBases
Home-page: https://github.com/yuvaneshkm/dbsconnector
Author: yuvaneshkm
Author-email: yuvaneshkm05@gmail.com
License: MIT
Project-URL: Bug Trackers, https://github.com/yuvaneshkm/dbsconnector/issues
Classifier: Programming Language :: Python :: 3.10
Classifier: Programming Language :: Python :: 3.11
Classifier: Operating System :: OS Independent
Requires-Python: >=3.9
License-File: LICENSE
Requires-Dist: numpy
Requires-Dist: openpyxl
Requires-Dist: pandas
Requires-Dist: pymongo
Requires-Dist: PyMySQL
Provides-Extra: testing
Requires-Dist: pytest>=7.1.3; extra == "testing"
Requires-Dist: mypy>=0.971; extra == "testing"
Requires-Dist: flake8>=5.0.4; extra == "testing"
Requires-Dist: tox>=3.24.4; extra == "testing"
Requires-Dist: black>=22.8.0; extra == "testing"
